CHANGES.txt
TODO.txt
bootstrap.py
buildout.cfg
setup.py
src/lovely/__init__.py
src/lovely.recipe.egg-info/PKG-INFO
src/lovely.recipe.egg-info/SOURCES.txt
src/lovely.recipe.egg-info/dependency_links.txt
src/lovely.recipe.egg-info/entry_points.txt
src/lovely.recipe.egg-info/namespace_packages.txt
src/lovely.recipe.egg-info/requires.txt
src/lovely.recipe.egg-info/top_level.txt
src/lovely.recipe.egg-info/zip-safe
src/lovely/recipe/__init__.py
src/lovely/recipe/testing.py
src/lovely/recipe/egg/README.txt
src/lovely/recipe/egg/__init__.py
src/lovely/recipe/egg/tests.py
src/lovely/recipe/fs/README.txt
src/lovely/recipe/fs/__init__.py
src/lovely/recipe/fs/mkdir-root.txt
src/lovely/recipe/fs/mkdir.py
src/lovely/recipe/fs/mkfile.py
src/lovely/recipe/fs/tests.py
src/lovely/recipe/i18n/README.txt
src/lovely/recipe/i18n/__init__.py
src/lovely/recipe/i18n/i18n.py
src/lovely/recipe/i18n/i18nextract.py
src/lovely/recipe/i18n/i18nmergeall.py
src/lovely/recipe/i18n/i18nstats.py
src/lovely/recipe/i18n/tests.py
src/lovely/recipe/importchecker/README.txt
src/lovely/recipe/importchecker/__init__.py
src/lovely/recipe/importchecker/app.py
src/lovely/recipe/importchecker/importchecker.py
src/lovely/recipe/importchecker/tests.py
src/lovely/recipe/zeo/server.py
src/lovely/recipe/zope/__init__.py
src/lovely/recipe/zope/template.py
src/lovely/recipe/zope/zope.py