Metadata-Version: 1.0
Name: lovely.recipe
Version: 1.0.0b3
Summary: set of helper recipies for zc.buildout
Home-page: http://launchpad.net/lovely.recipe
Author: Lovely Systems
Author-email: office@lovelysystems.com
License: ZPL 2.1
Keywords: buildout recipe filesystem i18n importchecker
Platform: UNKNOWN
